securepasswordgen/__init__.py
securepasswordgen/cli.py
securepasswordgen/generator.py
securepasswordgen-1.0.1.dist-info/licenses/LICENSE
securepasswordgen-1.0.1.dist-info/METADATA
securepasswordgen-1.0.1.dist-info/WHEEL
securepasswordgen-1.0.1.dist-info/entry_points.txt
securepasswordgen-1.0.1.dist-info/top_level.txt
securepasswordgen-1.0.1.dist-info/RECORD
