Metadata-Version: 2.4
Name: securepasswordgen
Version: 1.0.1
Summary: A secure password generator CLI tool.
Author-email: vishnu gopal <pg.vishnugopal@gmail.com>
License-Expression: MIT
Keywords: password,generator,cli,security
Requires-Python: >=3.7
License-File: LICENSE
Dynamic: license-file
